django_log_outgoing_requests-0.7.1.dist-info/licenses/LICENSE
log_outgoing_requests/__init__.py
log_outgoing_requests/admin.py
log_outgoing_requests/apps.py
log_outgoing_requests/compat.py
log_outgoing_requests/conf.py
log_outgoing_requests/config_reset.py
log_outgoing_requests/constants.py
log_outgoing_requests/datastructures.py
log_outgoing_requests/formatters.py
log_outgoing_requests/handlers.py
log_outgoing_requests/log_requests.py
log_outgoing_requests/models.py
log_outgoing_requests/py.typed
log_outgoing_requests/tasks.py
log_outgoing_requests/typing.py
log_outgoing_requests/utils.py
log_outgoing_requests/locale/nl/LC_MESSAGES/django.mo
log_outgoing_requests/locale/nl/LC_MESSAGES/django.po
log_outgoing_requests/management/__init__.py
log_outgoing_requests/management/commands/__init__.py
log_outgoing_requests/management/commands/prune_outgoing_request_logs.py
log_outgoing_requests/migrations/0001_initial.py
log_outgoing_requests/migrations/0002_outgoingrequestslogconfig_and_more.py
log_outgoing_requests/migrations/0003_alter_outgoingrequestslog_options_and_more.py
log_outgoing_requests/migrations/0004_alter_outgoingrequestslog_hostname_and_more.py
log_outgoing_requests/migrations/0005_alter_outgoingrequestslog_url.py
log_outgoing_requests/migrations/0006_outgoingrequestslogconfig_reset_db_save_after.py
log_outgoing_requests/migrations/__init__.py
log_outgoing_requests/static/log_outgoing_requests/css/admin.css
log_outgoing_requests/static/log_outgoing_requests/js/admin.js
django_log_outgoing_requests-0.7.1.dist-info/METADATA
django_log_outgoing_requests-0.7.1.dist-info/WHEEL
django_log_outgoing_requests-0.7.1.dist-info/top_level.txt
django_log_outgoing_requests-0.7.1.dist-info/RECORD
