Metadata-Version: 2.4
Name: django-log-outgoing-requests
Version: 0.7.1
Summary: Log outgoing requests made by the requests python library
Home-page: https://github.com/maykinmedia/django-log-outgoing-requests
Author: Maykin Media
Author-email: support@maykinmedia.nl
License: MIT
Project-URL: Documentation, http://django-log-outgoing-requests.readthedocs.io/en/latest/
Project-URL: Changelog, https://github.com/maykinmedia/django-log-outgoing-requests/blob/main/CHANGELOG.rst
Project-URL: Bug Tracker, https://github.com/maykinmedia/django-log-outgoing-requests/issues
Project-URL: Source Code, https://github.com/maykinmedia/django-log-outgoing-requests
Keywords: logging
Classifier: Development Status :: 3 - Alpha
Classifier: Framework :: Django
Classifier: Framework :: Django :: 3.2
Classifier: Framework :: Django :: 4.1
Classifier: Framework :: Django :: 4.2
Classifier: Intended Audience :: Developers
Classifier: Operating System :: Unix
Classifier: Operating System :: MacOS
Classifier: Operating System :: Microsoft :: Windows
Classifier: Programming Language :: Python :: 3.8
Classifier: Programming Language :: Python :: 3.9
Classifier: Programming Language :: Python :: 3.10
Classifier: Programming Language :: Python :: 3.11
Classifier: Topic :: Software Development :: Libraries :: Python Modules
License-File: LICENSE
Requires-Dist: django>=3.2
Requires-Dist: requests
Requires-Dist: django-appconf
Requires-Dist: django-solo
Provides-Extra: celery
Requires-Dist: celery; extra == "celery"
Provides-Extra: tests
Requires-Dist: pytest; extra == "tests"
Requires-Dist: pytest-django; extra == "tests"
Requires-Dist: pytest-mock; extra == "tests"
Requires-Dist: pyquery; extra == "tests"
Requires-Dist: tox; extra == "tests"
Requires-Dist: isort; extra == "tests"
Requires-Dist: black; extra == "tests"
Requires-Dist: flake8; extra == "tests"
Requires-Dist: freezegun; extra == "tests"
Requires-Dist: requests-mock; extra == "tests"
Provides-Extra: pep8
Requires-Dist: flake8; extra == "pep8"
Provides-Extra: coverage
Requires-Dist: pytest-cov; extra == "coverage"
Provides-Extra: docs
Requires-Dist: sphinx; extra == "docs"
Requires-Dist: sphinx-rtd-theme; extra == "docs"
Provides-Extra: release
Requires-Dist: bump2version; extra == "release"
Requires-Dist: twine; extra == "release"
Dynamic: license-file
